app_logger/__init__.py
app_logger/logger.py
app_logger-0.1.2.dist-info/LICENSE
app_logger-0.1.2.dist-info/WHEEL
app_logger-0.1.2.dist-info/METADATA
app_logger-0.1.2.dist-info/RECORD
