Metadata-Version: 2.1
Name: app-logger
Version: 0.1.2
Summary: A drop in logger configurable through environment variables
Home-page: https://github.com/TnLCommunity/app-logger
License: Apache-2.0
Keywords: logs,logging
Author: zackary stevens
Author-email: zackary.n.stevens@gmail.com
Requires-Python: >=3.6,<4.0
Classifier: License :: OSI Approved :: Apache Software License
Classifier: Programming Language :: Python :: 3
Classifier: Programming Language :: Python :: 3.6
Classifier: Programming Language :: Python :: 3.7
Classifier: Programming Language :: Python :: 3.8
Requires-Dist: python-json-logger (>=0.1.11,<0.2.0)
Project-URL: Repository, https://github.com/TnLCommunity/app-logger
